FRET_board-0.0.4.dist-info/DESCRIPTION.rst
FRET_board-0.0.4.dist-info/METADATA
FRET_board-0.0.4.dist-info/RECORD
FRET_board-0.0.4.dist-info/WHEEL
FRET_board-0.0.4.dist-info/entry_points.txt
FRET_board-0.0.4.dist-info/metadata.json
FRET_board-0.0.4.dist-info/top_level.txt
FRETboard/FretReport.py
FRETboard/Gui.py
FRETboard/MainTable.py
FRETboard/__init__.py
FRETboard/__main__.py
FRETboard/algorithms.yml
FRETboard/async_test.py
FRETboard/helper_functions.py
FRETboard/io_functions.py
FRETboard/lsh_bin_selection.py
FRETboard/main.py
FRETboard/minimal_example.py
FRETboard/algorithms/EdgeAwareHmm.py
FRETboard/algorithms/EdgeAwareHmm_backup.py
FRETboard/algorithms/EdgeAwareHmm_old.py
FRETboard/algorithms/VanillaHmm.py
FRETboard/algorithms/VanillaHmm_backup.py
FRETboard/js_widgets/download_csv.js
FRETboard/js_widgets/download_datzip.js
FRETboard/js_widgets/download_model.js
FRETboard/js_widgets/download_report.js
FRETboard/js_widgets/upload.js
FRETboard/js_widgets/upload_model.js
FRETboard/js_widgets/upload_old.js
FRETboard/templates/index.html
FRETboard/templates/report_template.html
