Metadata-Version: 2.0
Name: FRET-board
Version: 0.0.4
Summary: Supervise FRET event detection algorithms
Home-page: https://github.com/cvdelannoy/FRETboard
Author: Carlos de Lannoy
Author-email: carlos.delannoy@wur.nl
License: MIT
Keywords: FRET Forster resonance energy transfer supervised machine learning
Platform: UNKNOWN
Classifier: Programming Language :: Python :: 3
Classifier: License :: OSI Approved :: MIT License
Requires-Dist: numpy (==1.17.3)
Requires-Dist: pandas (==0.25.3)
Requires-Dist: pomegranate (==0.11.2)
Requires-Dist: bokeh (==1.4.0)
Requires-Dist: cached-property (==1.5.1)
Requires-Dist: tabulate (==0.8.3)
Requires-Dist: tornado (==6.0.3)
